{ "columns":33,
 "editorsettings":
    {
     "export":
        {
         "format":"",
         "target":"."
        }
    },
 "image":"terrain.png",
 "imageheight":640,
 "imagewidth":1056,
 "margin":0,
 "name":"terrain",
 "spacing":0,
 "terrains":[
        {
         "name":"Snow Water",
         "tile":0
        }, 
        {
         "name":"Snow Water Light",
         "tile":174
        }, 
        {
         "name":"Ice Water",
         "tile":9
        }, 
        {
         "name":"Snow Dirt",
         "tile":18
        }, 
        {
         "name":"Snow Paved",
         "tile":21
        }, 
        {
         "name":"Snow Paved 2",
         "tile":348
        }, 
        {
         "name":"Snow Paved 3",
         "tile":351
        }, 
        {
         "name":"Snow Chips",
         "tile":183
        }, 
        {
         "name":"Snow Edge",
         "tile":27
        }, 
        {
         "name":"Snow Sand",
         "tile":186
        }, 
        {
         "name":"Snow Edge Wet",
         "tile":30
        }, 
        {
         "name":"Snow Frozen Water",
         "tile":354
        }, 
        {
         "name":"Water",
         "tile":165
        }, 
        {
         "name":"Grass",
         "tile":24
        }, 
        {
         "name":"Weeds",
         "tile":192
        }],
 "tilecount":660,
 "tiledversion":"2020.05.29",
 "tileheight":32,
 "tiles":[
        {
         "animation":[
                {
                 "duration":250,
                 "tileid":0
                }, 
                {
                 "duration":250,
                 "tileid":3
                }, 
                {
                 "duration":250,
                 "tileid":6
                }],
         "id":0
        }, 
        {
         "animation":[
                {
                 "duration":250,
                 "tileid":1
                }, 
                {
                 "duration":250,
                 "tileid":4
                }, 
                {
                 "duration":250,
                 "tileid":7
                }],
         "id":1,
         "terrain":[0, 0, 0, -1]
        }, 
        {
         "animation":[
                {
                 "duration":250,
                 "tileid":2
                }, 
                {
                 "duration":250,
                 "tileid":5
                }, 
                {
                 "duration":250,
                 "tileid":8
                }],
         "id":2,
         "terrain":[0, 0, -1, 0]
        }, 
        {
         "id":10,
         "terrain":[2, 2, 2, -1]
        }, 
        {
         "id":11,
         "terrain":[2, 2, -1, 2]
        }, 
        {
         "id":19,
         "terrain":[3, 3, 3, -1]
        }, 
        {
         "id":20,
         "terrain":[3, 3, -1, 3]
        }, 
        {
         "id":22,
         "terrain":[4, 4, 4, -1]
        }, 
        {
         "id":23,
         "terrain":[4, 4, -1, 4]
        }, 
        {
         "id":25,
         "terrain":[13, 13, 13, -1]
        }, 
        {
         "id":26,
         "terrain":[13, 13, -1, 13]
        }, 
        {
         "id":28,
         "terrain":[8, 8, 8, -1]
        }, 
        {
         "id":29,
         "terrain":[8, 8, -1, 8]
        }, 
        {
         "id":31,
         "terrain":[10, 10, 10, -1]
        }, 
        {
         "id":32,
         "terrain":[10, 10, -1, 10]
        }, 
        {
         "animation":[
                {
                 "duration":250,
                 "tileid":34
                }, 
                {
                 "duration":250,
                 "tileid":37
                }, 
                {
                 "duration":250,
                 "tileid":40
                }],
         "id":34,
         "terrain":[0, -1, 0, 0]
        }, 
        {
         "animation":[
                {
                 "duration":250,
                 "tileid":35
                }, 
                {
                 "duration":250,
                 "tileid":38
                }, 
                {
                 "duration":250,
                 "tileid":41
                }],
         "id":35,
         "terrain":[-1, 0, 0, 0]
        }, 
        {
         "id":43,
         "terrain":[2, -1, 2, 2]
        }, 
        {
         "id":44,
         "terrain":[-1, 2, 2, 2]
        }, 
        {
         "id":52,
         "terrain":[3, -1, 3, 3]
        }, 
        {
         "id":53,
         "terrain":[-1, 3, 3, 3]
        }, 
        {
         "id":55,
         "terrain":[4, -1, 4, 4]
        }, 
        {
         "id":56,
         "terrain":[-1, 4, 4, 4]
        }, 
        {
         "id":58,
         "terrain":[13, -1, 13, 13]
        }, 
        {
         "id":59,
         "terrain":[-1, 13, 13, 13]
        }, 
        {
         "id":61,
         "terrain":[8, -1, 8, 8]
        }, 
        {
         "id":62,
         "terrain":[-1, 8, 8, 8]
        }, 
        {
         "id":64,
         "terrain":[10, -1, 10, 10]
        }, 
        {
         "id":65,
         "terrain":[-1, 10, 10, 10]
        }, 
        {
         "animation":[
                {
                 "duration":250,
                 "tileid":66
                }, 
                {
                 "duration":250,
                 "tileid":69
                }, 
                {
                 "duration":250,
                 "tileid":72
                }],
         "id":66,
         "terrain":[-1, -1, -1, 0]
        }, 
        {
         "animation":[
                {
                 "duration":250,
                 "tileid":67
                }, 
                {
                 "duration":250,
                 "tileid":70
                }, 
                {
                 "duration":250,
                 "tileid":73
                }],
         "id":67,
         "terrain":[-1, -1, 0, 0]
        }, 
        {
         "animation":[
                {
                 "duration":250,
                 "tileid":68
                }, 
                {
                 "duration":250,
                 "tileid":71
                }, 
                {
                 "duration":250,
                 "tileid":74
                }],
         "id":68,
         "terrain":[-1, -1, 0, -1]
        }, 
        {
         "id":75,
         "terrain":[-1, -1, -1, 2]
        }, 
        {
         "id":76,
         "terrain":[-1, -1, 2, 2]
        }, 
        {
         "id":77,
         "terrain":[-1, -1, 2, -1]
        }, 
        {
         "id":84,
         "terrain":[-1, -1, -1, 3]
        }, 
        {
         "id":85,
         "terrain":[-1, -1, 3, 3]
        }, 
        {
         "id":86,
         "terrain":[-1, -1, 3, -1]
        }, 
        {
         "id":87,
         "terrain":[-1, -1, -1, 4]
        }, 
        {
         "id":88,
         "terrain":[-1, -1, 4, 4]
        }, 
        {
         "id":89,
         "terrain":[-1, -1, 4, -1]
        }, 
        {
         "id":90,
         "terrain":[-1, -1, -1, 13]
        }, 
        {
         "id":91,
         "terrain":[-1, -1, 13, 13]
        }, 
        {
         "id":92,
         "terrain":[-1, -1, 13, -1]
        }, 
        {
         "id":93,
         "terrain":[-1, -1, -1, 8]
        }, 
        {
         "id":94,
         "terrain":[-1, -1, 8, 8]
        }, 
        {
         "id":95,
         "terrain":[-1, -1, 8, -1]
        }, 
        {
         "id":96,
         "terrain":[-1, -1, -1, 10]
        }, 
        {
         "id":97,
         "terrain":[-1, -1, 10, 10]
        }, 
        {
         "id":98,
         "terrain":[-1, -1, 10, -1]
        }, 
        {
         "animation":[
                {
                 "duration":250,
                 "tileid":99
                }, 
                {
                 "duration":250,
                 "tileid":102
                }, 
                {
                 "duration":250,
                 "tileid":105
                }],
         "id":99,
         "terrain":[-1, 0, -1, 0]
        }, 
        {
         "animation":[
                {
                 "duration":250,
                 "tileid":100
                }, 
                {
                 "duration":250,
                 "tileid":103
                }, 
                {
                 "duration":250,
                 "tileid":106
                }],
         "id":100,
         "terrain":[0, 0, 0, 0]
        }, 
        {
         "animation":[
                {
                 "duration":250,
                 "tileid":101
                }, 
                {
                 "duration":250,
                 "tileid":104
                }, 
                {
                 "duration":250,
                 "tileid":107
                }],
         "id":101,
         "terrain":[0, -1, 0, -1]
        }, 
        {
         "id":108,
         "terrain":[-1, 2, -1, 2]
        }, 
        {
         "id":109,
         "terrain":[2, 2, 2, 2]
        }, 
        {
         "id":110,
         "terrain":[2, -1, 2, -1]
        }, 
        {
         "id":117,
         "terrain":[-1, 3, -1, 3]
        }, 
        {
         "id":118,
         "terrain":[3, 3, 3, 3]
        }, 
        {
         "id":119,
         "terrain":[3, -1, 3, -1]
        }, 
        {
         "id":120,
         "terrain":[-1, 4, -1, 4]
        }, 
        {
         "id":121,
         "terrain":[4, 4, 4, 4]
        }, 
        {
         "id":122,
         "terrain":[4, -1, 4, -1]
        }, 
        {
         "id":123,
         "terrain":[-1, 13, -1, 13]
        }, 
        {
         "id":124,
         "terrain":[13, 13, 13, 13]
        }, 
        {
         "id":125,
         "terrain":[13, -1, 13, -1]
        }, 
        {
         "id":126,
         "terrain":[-1, 8, -1, 8]
        }, 
        {
         "id":127,
         "terrain":[8, 8, 8, 8]
        }, 
        {
         "id":128,
         "terrain":[8, -1, 8, -1]
        }, 
        {
         "id":129,
         "terrain":[-1, 10, -1, 10]
        }, 
        {
         "id":130,
         "terrain":[10, 10, 10, 10]
        }, 
        {
         "id":131,
         "terrain":[10, -1, 10, -1]
        }, 
        {
         "animation":[
                {
                 "duration":250,
                 "tileid":132
                }, 
                {
                 "duration":250,
                 "tileid":135
                }, 
                {
                 "duration":250,
                 "tileid":138
                }],
         "id":132,
         "terrain":[-1, 0, -1, -1]
        }, 
        {
         "animation":[
                {
                 "duration":250,
                 "tileid":133
                }, 
                {
                 "duration":250,
                 "tileid":136
                }, 
                {
                 "duration":250,
                 "tileid":139
                }],
         "id":133,
         "terrain":[0, 0, -1, -1]
        }, 
        {
         "animation":[
                {
                 "duration":250,
                 "tileid":134
                }, 
                {
                 "duration":250,
                 "tileid":137
                }, 
                {
                 "duration":250,
                 "tileid":140
                }],
         "id":134,
         "terrain":[0, -1, -1, -1]
        }, 
        {
         "id":141,
         "terrain":[-1, 2, -1, -1]
        }, 
        {
         "id":142,
         "terrain":[2, 2, -1, -1]
        }, 
        {
         "id":143,
         "terrain":[2, -1, -1, -1]
        }, 
        {
         "id":150,
         "terrain":[-1, 3, -1, -1]
        }, 
        {
         "id":151,
         "terrain":[3, 3, -1, -1]
        }, 
        {
         "id":152,
         "terrain":[3, -1, -1, -1]
        }, 
        {
         "id":153,
         "terrain":[-1, 4, -1, -1]
        }, 
        {
         "id":154,
         "terrain":[4, 4, -1, -1]
        }, 
        {
         "id":155,
         "terrain":[4, -1, -1, -1]
        }, 
        {
         "id":156,
         "terrain":[-1, 13, -1, -1]
        }, 
        {
         "id":157,
         "terrain":[13, 13, -1, -1]
        }, 
        {
         "id":158,
         "terrain":[13, -1, -1, -1]
        }, 
        {
         "id":159,
         "terrain":[-1, 8, -1, -1]
        }, 
        {
         "id":160,
         "terrain":[8, 8, -1, -1]
        }, 
        {
         "id":161,
         "terrain":[8, -1, -1, -1]
        }, 
        {
         "id":162,
         "terrain":[-1, 10, -1, -1]
        }, 
        {
         "id":163,
         "terrain":[10, 10, -1, -1]
        }, 
        {
         "id":164,
         "terrain":[10, -1, -1, -1]
        }, 
        {
         "animation":[
                {
                 "duration":250,
                 "tileid":165
                }, 
                {
                 "duration":250,
                 "tileid":168
                }, 
                {
                 "duration":250,
                 "tileid":171
                }],
         "id":165
        }, 
        {
         "animation":[
                {
                 "duration":250,
                 "tileid":166
                }, 
                {
                 "duration":250,
                 "tileid":169
                }, 
                {
                 "duration":250,
                 "tileid":172
                }],
         "id":166,
         "terrain":[12, 12, 12, -1]
        }, 
        {
         "animation":[
                {
                 "duration":250,
                 "tileid":167
                }, 
                {
                 "duration":250,
                 "tileid":170
                }, 
                {
                 "duration":250,
                 "tileid":173
                }],
         "id":167,
         "terrain":[12, 12, -1, 12]
        }, 
        {
         "animation":[
                {
                 "duration":250,
                 "tileid":175
                }, 
                {
                 "duration":250,
                 "tileid":178
                }, 
                {
                 "duration":250,
                 "tileid":181
                }],
         "id":175,
         "terrain":[1, 1, 1, -1]
        }, 
        {
         "animation":[
                {
                 "duration":250,
                 "tileid":176
                }, 
                {
                 "duration":250,
                 "tileid":179
                }, 
                {
                 "duration":250,
                 "tileid":182
                }],
         "id":176,
         "terrain":[1, 1, -1, 1]
        }, 
        {
         "id":184,
         "terrain":[7, 7, 7, -1]
        }, 
        {
         "id":185,
         "terrain":[7, 7, -1, 7]
        }, 
        {
         "id":187,
         "terrain":[9, 9, 9, -1]
        }, 
        {
         "id":188,
         "terrain":[9, 9, -1, 9]
        }, 
        {
         "id":193,
         "terrain":[14, 14, 14, -1]
        }, 
        {
         "id":194,
         "terrain":[14, 14, -1, 14]
        }, 
        {
         "animation":[
                {
                 "duration":250,
                 "tileid":199
                }, 
                {
                 "duration":250,
                 "tileid":202
                }, 
                {
                 "duration":250,
                 "tileid":205
                }],
         "id":199,
         "terrain":[12, -1, 12, 12]
        }, 
        {
         "animation":[
                {
                 "duration":250,
                 "tileid":200
                }, 
                {
                 "duration":250,
                 "tileid":203
                }, 
                {
                 "duration":250,
                 "tileid":206
                }],
         "id":200,
         "terrain":[-1, 12, 12, 12]
        }, 
        {
         "animation":[
                {
                 "duration":250,
                 "tileid":208
                }, 
                {
                 "duration":250,
                 "tileid":211
                }, 
                {
                 "duration":250,
                 "tileid":214
                }],
         "id":208,
         "terrain":[1, -1, 1, 1]
        }, 
        {
         "animation":[
                {
                 "duration":250,
                 "tileid":209
                }, 
                {
                 "duration":250,
                 "tileid":212
                }, 
                {
                 "duration":250,
                 "tileid":215
                }],
         "id":209,
         "terrain":[-1, 1, 1, 1]
        }, 
        {
         "id":217,
         "terrain":[7, -1, 7, 7]
        }, 
        {
         "id":218,
         "terrain":[-1, 7, 7, 7]
        }, 
        {
         "id":220,
         "terrain":[9, -1, 9, 9]
        }, 
        {
         "id":221,
         "terrain":[-1, 9, 9, 9]
        }, 
        {
         "id":226,
         "terrain":[14, -1, 14, 14]
        }, 
        {
         "id":227,
         "terrain":[-1, 14, 14, 14]
        }, 
        {
         "animation":[
                {
                 "duration":250,
                 "tileid":231
                }, 
                {
                 "duration":250,
                 "tileid":234
                }, 
                {
                 "duration":250,
                 "tileid":237
                }],
         "id":231,
         "terrain":[-1, -1, -1, 12]
        }, 
        {
         "animation":[
                {
                 "duration":250,
                 "tileid":232
                }, 
                {
                 "duration":250,
                 "tileid":235
                }, 
                {
                 "duration":250,
                 "tileid":238
                }],
         "id":232,
         "terrain":[-1, -1, 12, 12]
        }, 
        {
         "animation":[
                {
                 "duration":250,
                 "tileid":233
                }, 
                {
                 "duration":250,
                 "tileid":236
                }, 
                {
                 "duration":250,
                 "tileid":239
                }],
         "id":233,
         "terrain":[-1, -1, 12, -1]
        }, 
        {
         "animation":[
                {
                 "duration":250,
                 "tileid":240
                }, 
                {
                 "duration":250,
                 "tileid":243
                }, 
                {
                 "duration":250,
                 "tileid":246
                }],
         "id":240,
         "terrain":[-1, -1, -1, 1]
        }, 
        {
         "animation":[
                {
                 "duration":250,
                 "tileid":241
                }, 
                {
                 "duration":250,
                 "tileid":244
                }, 
                {
                 "duration":250,
                 "tileid":247
                }],
         "id":241,
         "terrain":[-1, -1, 1, 1]
        }, 
        {
         "animation":[
                {
                 "duration":250,
                 "tileid":242
                }, 
                {
                 "duration":250,
                 "tileid":245
                }, 
                {
                 "duration":250,
                 "tileid":248
                }],
         "id":242,
         "terrain":[-1, -1, 1, -1]
        }, 
        {
         "id":249,
         "terrain":[-1, -1, -1, 7]
        }, 
        {
         "id":250,
         "terrain":[-1, -1, 7, 7]
        }, 
        {
         "id":251,
         "terrain":[-1, -1, 7, -1]
        }, 
        {
         "id":252,
         "terrain":[-1, -1, -1, 9]
        }, 
        {
         "id":253,
         "terrain":[-1, -1, 9, 9]
        }, 
        {
         "id":254,
         "terrain":[-1, -1, 9, -1]
        }, 
        {
         "id":258,
         "terrain":[-1, -1, -1, 14]
        }, 
        {
         "id":259,
         "terrain":[-1, -1, 14, 14]
        }, 
        {
         "id":260,
         "terrain":[-1, -1, 14, -1]
        }, 
        {
         "animation":[
                {
                 "duration":250,
                 "tileid":264
                }, 
                {
                 "duration":250,
                 "tileid":267
                }, 
                {
                 "duration":250,
                 "tileid":270
                }],
         "id":264,
         "terrain":[-1, 12, -1, 12]
        }, 
        {
         "animation":[
                {
                 "duration":250,
                 "tileid":265
                }, 
                {
                 "duration":250,
                 "tileid":268
                }, 
                {
                 "duration":250,
                 "tileid":271
                }],
         "id":265,
         "terrain":[12, 12, 12, 12]
        }, 
        {
         "animation":[
                {
                 "duration":250,
                 "tileid":266
                }, 
                {
                 "duration":250,
                 "tileid":269
                }, 
                {
                 "duration":250,
                 "tileid":272
                }],
         "id":266,
         "terrain":[12, -1, 12, -1]
        }, 
        {
         "animation":[
                {
                 "duration":250,
                 "tileid":273
                }, 
                {
                 "duration":250,
                 "tileid":276
                }, 
                {
                 "duration":250,
                 "tileid":279
                }],
         "id":273,
         "terrain":[-1, 1, -1, 1]
        }, 
        {
         "animation":[
                {
                 "duration":250,
                 "tileid":274
                }, 
                {
                 "duration":250,
                 "tileid":277
                }, 
                {
                 "duration":250,
                 "tileid":280
                }],
         "id":274,
         "terrain":[1, 1, 1, 1]
        }, 
        {
         "animation":[
                {
                 "duration":250,
                 "tileid":275
                }, 
                {
                 "duration":250,
                 "tileid":278
                }, 
                {
                 "duration":250,
                 "tileid":281
                }],
         "id":275,
         "terrain":[1, -1, 1, -1]
        }, 
        {
         "id":282,
         "terrain":[-1, 7, -1, 7]
        }, 
        {
         "id":283,
         "terrain":[7, 7, 7, 7]
        }, 
        {
         "id":284,
         "terrain":[7, -1, 7, -1]
        }, 
        {
         "id":285,
         "terrain":[-1, 9, -1, 9]
        }, 
        {
         "id":286,
         "terrain":[9, 9, 9, 9]
        }, 
        {
         "id":287,
         "terrain":[9, -1, 9, -1]
        }, 
        {
         "id":291,
         "terrain":[-1, 14, -1, 14]
        }, 
        {
         "id":292,
         "terrain":[14, 14, 14, 14]
        }, 
        {
         "id":293,
         "terrain":[14, -1, 14, -1]
        }, 
        {
         "animation":[
                {
                 "duration":250,
                 "tileid":297
                }, 
                {
                 "duration":250,
                 "tileid":300
                }, 
                {
                 "duration":250,
                 "tileid":303
                }],
         "id":297,
         "terrain":[-1, 12, -1, -1]
        }, 
        {
         "animation":[
                {
                 "duration":250,
                 "tileid":298
                }, 
                {
                 "duration":250,
                 "tileid":301
                }, 
                {
                 "duration":250,
                 "tileid":304
                }],
         "id":298,
         "terrain":[12, 12, -1, -1]
        }, 
        {
         "animation":[
                {
                 "duration":250,
                 "tileid":299
                }, 
                {
                 "duration":250,
                 "tileid":302
                }, 
                {
                 "duration":250,
                 "tileid":305
                }],
         "id":299,
         "terrain":[12, -1, -1, -1]
        }, 
        {
         "animation":[
                {
                 "duration":250,
                 "tileid":306
                }, 
                {
                 "duration":250,
                 "tileid":309
                }, 
                {
                 "duration":250,
                 "tileid":312
                }],
         "id":306,
         "terrain":[-1, 1, -1, -1]
        }, 
        {
         "animation":[
                {
                 "duration":250,
                 "tileid":307
                }, 
                {
                 "duration":250,
                 "tileid":310
                }, 
                {
                 "duration":250,
                 "tileid":313
                }],
         "id":307,
         "terrain":[1, 1, -1, -1]
        }, 
        {
         "animation":[
                {
                 "duration":250,
                 "tileid":308
                }, 
                {
                 "duration":250,
                 "tileid":311
                }, 
                {
                 "duration":250,
                 "tileid":314
                }],
         "id":308,
         "terrain":[1, -1, -1, -1]
        }, 
        {
         "id":315,
         "terrain":[-1, 7, -1, -1]
        }, 
        {
         "id":316,
         "terrain":[7, 7, -1, -1]
        }, 
        {
         "id":317,
         "terrain":[7, -1, -1, -1]
        }, 
        {
         "id":318,
         "terrain":[-1, 9, -1, -1]
        }, 
        {
         "id":319,
         "terrain":[9, 9, -1, -1]
        }, 
        {
         "id":320,
         "terrain":[9, -1, -1, -1]
        }, 
        {
         "id":324,
         "terrain":[-1, 14, -1, -1]
        }, 
        {
         "id":325,
         "terrain":[14, 14, -1, -1]
        }, 
        {
         "id":326,
         "terrain":[14, -1, -1, -1]
        }, 
        {
         "id":349,
         "terrain":[5, 5, 5, -1]
        }, 
        {
         "id":350,
         "terrain":[5, 5, -1, 5]
        }, 
        {
         "id":352,
         "terrain":[6, 6, 6, -1]
        }, 
        {
         "id":353,
         "terrain":[6, 6, -1, 6]
        }, 
        {
         "id":355,
         "terrain":[11, 11, 11, -1]
        }, 
        {
         "id":356,
         "terrain":[11, 11, -1, 11]
        }, 
        {
         "id":382,
         "terrain":[5, -1, 5, 5]
        }, 
        {
         "id":383,
         "terrain":[-1, 5, 5, 5]
        }, 
        {
         "id":385,
         "terrain":[6, -1, 6, 6]
        }, 
        {
         "id":386,
         "terrain":[-1, 6, 6, 6]
        }, 
        {
         "id":388,
         "terrain":[11, -1, 11, 11]
        }, 
        {
         "id":389,
         "terrain":[-1, 11, 11, 11]
        }, 
        {
         "id":414,
         "terrain":[-1, -1, -1, 5]
        }, 
        {
         "id":415,
         "terrain":[-1, -1, 5, 5]
        }, 
        {
         "id":416,
         "terrain":[-1, -1, 5, -1]
        }, 
        {
         "id":417,
         "terrain":[-1, -1, -1, 6]
        }, 
        {
         "id":418,
         "terrain":[-1, -1, 6, 6]
        }, 
        {
         "id":419,
         "terrain":[-1, -1, 6, -1]
        }, 
        {
         "id":420,
         "terrain":[-1, -1, -1, 11]
        }, 
        {
         "id":421,
         "terrain":[-1, -1, 11, 11]
        }, 
        {
         "id":422,
         "terrain":[-1, -1, 11, -1]
        }, 
        {
         "id":447,
         "terrain":[-1, 5, -1, 5]
        }, 
        {
         "id":448,
         "terrain":[5, 5, 5, 5]
        }, 
        {
         "id":449,
         "terrain":[5, -1, 5, -1]
        }, 
        {
         "id":450,
         "terrain":[-1, 6, -1, 6]
        }, 
        {
         "id":451,
         "terrain":[6, 6, 6, 6]
        }, 
        {
         "id":452,
         "terrain":[6, -1, 6, -1]
        }, 
        {
         "id":453,
         "terrain":[-1, 11, -1, 11]
        }, 
        {
         "id":454,
         "terrain":[11, 11, 11, 11]
        }, 
        {
         "id":455,
         "terrain":[11, -1, 11, -1]
        }, 
        {
         "id":480,
         "terrain":[-1, 5, -1, -1]
        }, 
        {
         "id":481,
         "terrain":[5, 5, -1, -1]
        }, 
        {
         "id":482,
         "terrain":[5, -1, -1, -1]
        }, 
        {
         "id":483,
         "terrain":[-1, 6, -1, -1]
        }, 
        {
         "id":484,
         "terrain":[6, 6, -1, -1]
        }, 
        {
         "id":485,
         "terrain":[6, -1, -1, -1]
        }, 
        {
         "id":486,
         "terrain":[-1, 11, -1, -1]
        }, 
        {
         "id":487,
         "terrain":[11, 11, -1, -1]
        }, 
        {
         "id":488,
         "terrain":[11, -1, -1, -1]
        }],
 "tilewidth":32,
 "type":"tileset",
 "version":1.2
}